llama_index/packs/amazon_product_extraction/__init__.py
llama_index/packs/amazon_product_extraction/base.py
llama_index_packs_amazon_product_extraction-0.4.1.dist-info/METADATA
llama_index_packs_amazon_product_extraction-0.4.1.dist-info/WHEEL
llama_index_packs_amazon_product_extraction-0.4.1.dist-info/licenses/LICENSE
llama_index_packs_amazon_product_extraction-0.4.1.dist-info/RECORD
