Metadata-Version: 2.4
Name: llama-index-packs-amazon-product-extraction
Version: 0.4.1
Summary: llama-index packs amazon_product_extraction integration
Author-email: Your Name <you@example.com>
Maintainer: jerryjliu
License-Expression: MIT
License-File: LICENSE
Keywords: amazon,extraction,product
Requires-Python: <4.0,>=3.9
Requires-Dist: llama-index-core<0.15,>=0.13.0
Requires-Dist: llama-index-multi-modal-llms-openai<0.7,>=0.6.0
Requires-Dist: pyppeteer<2,>=1.0.2
